qesdk/__init__.py
qesdk/aio_api.py
qesdk/api.py
qesdk/client.py
qesdk/config.py
qesdk/qedata.thrift
qesdk/utils.py
qesdk-0.1.21.dist-info/licenses/LICENSE
qesdk-0.1.21.dist-info/METADATA
qesdk-0.1.21.dist-info/WHEEL
qesdk-0.1.21.dist-info/top_level.txt
qesdk-0.1.21.dist-info/RECORD
