Metadata-Version: 2.4
Name: qesdk
Version: 0.1.21
Summary: Quantease SDK for quants
Author-email: Scott Zhang <scott2011@qq.com>
License: MIT License
Project-URL: Homepage, https://github.com/quantease/qesdk
Project-URL: Bug Tracker, https://github.com/quantease/qesdk/issues
Classifier: Programming Language :: Python :: 3
Classifier: License :: OSI Approved :: MIT License
Classifier: Operating System :: OS Independent
Requires-Python: >=3.7
License-File: LICENSE
Requires-Dist: msgpack_python>=0.5.6
Requires-Dist: nest_asyncio>=1.5.5
Requires-Dist: numpy>=1.19.2
Requires-Dist: pandas>=1.3.5
Requires-Dist: thriftpy2>=0.4.14
Dynamic: license-file
